coord2loc/__init__.py
coord2loc/data.py
coord2loc/py.typed
coord2loc-0.0.3.dist-info/METADATA
coord2loc-0.0.3.dist-info/WHEEL
coord2loc-0.0.3.dist-info/licenses/LICENSE
coord2loc-0.0.3.dist-info/RECORD
