Metadata-Version: 2.4
Name: coord2loc
Version: 0.0.3
Summary: Convert latitude and longitude into localities like countries and states
Author-email: James Hale <james+coord2loc@hale.zip>
License-File: LICENSE
Requires-Python: >=3.9
Requires-Dist: msgpack>=1.1.0
Requires-Dist: shapely>=2.0.7
Provides-Extra: all
Requires-Dist: coord2loc-can; extra == 'all'
Requires-Dist: coord2loc-usa; extra == 'all'
Provides-Extra: can
Requires-Dist: coord2loc-can; extra == 'can'
Provides-Extra: usa
Requires-Dist: coord2loc-usa; extra == 'usa'
